afkafe/__init__.py
afkafe/__main__.py
afkafe/utils.py
afkafe-1.1.dist-info/METADATA
afkafe-1.1.dist-info/WHEEL
afkafe-1.1.dist-info/entry_points.txt
afkafe-1.1.dist-info/licenses/LICENSE
afkafe-1.1.dist-info/RECORD
