Metadata-Version: 2.4
Name: afkafe
Version: 1.1
Summary: AFKafé orders caffeine for you if you idle too long!
Project-URL: Homepage, https://github.com/Graeme22/afkafe
Author-email: Graeme Holliday <graeme@tastyware.dev>
License: MIT License
License-File: LICENSE
Requires-Python: >=3.9
Requires-Dist: pynput>=1.8.1
Requires-Dist: terminal-shop>=1.6.0
Requires-Dist: typer>=0.15.2
